onoffmonitordevice/__init__.py
onoffmonitordevice/__main__.py
onoffmonitordevice/device.py
onoffmonitordevice/exceptions.py
onoffmonitordevice/monitor.py
onoffmonitordevice-0.3.0.dist-info/LICENSE
onoffmonitordevice-0.3.0.dist-info/METADATA
onoffmonitordevice-0.3.0.dist-info/WHEEL
onoffmonitordevice-0.3.0.dist-info/entry_points.txt
onoffmonitordevice-0.3.0.dist-info/top_level.txt
onoffmonitordevice-0.3.0.dist-info/RECORD
