Metadata-Version: 2.1
Name: onoffmonitordevice
Version: 0.3.0
Summary: Monitor the on/off status of devices and report to the server
Author: Joe Greaves
License: The Clear BSD License
Project-URL: Homepage, https://github.com/Grvs44/onoffmonitordevice
Classifier: Programming Language :: Python :: 3
Classifier: License :: OSI Approved :: BSD License
Classifier: Operating System :: POSIX :: Linux
Requires-Python: <4,>=3.11
License-File: LICENSE
Requires-Dist: requests (>=2.31.0)
Requires-Dist: keyring (>=24.2.0)
Requires-Dist: RPi.GPIO (>=0.7.1)
Requires-Dist: keyrings.alt (>=4.2.0)
